README.md
setup.py
tap_logmeinrescue/__init__.py
tap_logmeinrescue/client.py
tap_logmeinrescue/logger.py
tap_logmeinrescue/state.py
tap_logmeinrescue.egg-info/PKG-INFO
tap_logmeinrescue.egg-info/SOURCES.txt
tap_logmeinrescue.egg-info/dependency_links.txt
tap_logmeinrescue.egg-info/entry_points.txt
tap_logmeinrescue.egg-info/requires.txt
tap_logmeinrescue.egg-info/top_level.txt
tap_logmeinrescue/schemas/session_report.json
tap_logmeinrescue/schemas/technician_survey_report.json
tap_logmeinrescue/schemas/technicians.json
tap_logmeinrescue/schemas/transferred_sessions_extended_report.json
tap_logmeinrescue/streams/__init__.py
tap_logmeinrescue/streams/base.py
tap_logmeinrescue/streams/session_report.py
tap_logmeinrescue/streams/technician_survey_report.py
tap_logmeinrescue/streams/technicians.py
tap_logmeinrescue/streams/transferred_sessions_extended_report.py