Metadata-Version: 2.1
Name: tap-logmeinrescue
Version: 0.0.8
Summary: Singer.io tap for extracting data from the LogMeIn Rescue API
Home-page: http://fishtownanalytics.com
Author: Fishtown Analytics
License: UNKNOWN
Platform: UNKNOWN
Classifier: Programming Language :: Python :: 3 :: Only
Provides-Extra: dev
